httpython/__init__.py
httpython/documents.py
httpython/requests.py
httpython/servers.py
httpython/structures.py
httpython-0.2.7.dist-info/LICENSE
httpython-0.2.7.dist-info/METADATA
httpython-0.2.7.dist-info/WHEEL
httpython-0.2.7.dist-info/top_level.txt
httpython-0.2.7.dist-info/RECORD
