Metadata-Version: 2.1
Name: httpython
Version: 0.2.7
Summary: A simple-to-use framework for http and https servers
Home-page: https://github.com/jaobernardi/Httpy
Author: Jão Bernardi
Author-email: joao_bernardi@outlook.com
License: UNKNOWN
Platform: UNKNOWN
Classifier: Programming Language :: Python :: 3
Classifier: License :: OSI Approved :: MIT License
Classifier: Operating System :: OS Independent
Requires-Python: >=3.6
